llm_nomic_api_embed.py
llm_nomic_api_embed-0.3.dist-info/LICENSE
llm_nomic_api_embed-0.3.dist-info/METADATA
llm_nomic_api_embed-0.3.dist-info/WHEEL
llm_nomic_api_embed-0.3.dist-info/entry_points.txt
llm_nomic_api_embed-0.3.dist-info/top_level.txt
llm_nomic_api_embed-0.3.dist-info/RECORD
