Metadata-Version: 2.1
Name: llm-nomic-api-embed
Version: 0.3
Summary: Create embeddings using the Nomic API
Author: Simon Willison
License: Apache-2.0
Project-URL: Homepage, https://github.com/simonw/llm-nomic-api-embed
Project-URL: Changelog, https://github.com/simonw/llm-nomic-api-embed/releases
Project-URL: Issues, https://github.com/simonw/llm-nomic-api-embed/issues
Project-URL: CI, https://github.com/simonw/llm-nomic-api-embed/actions
Classifier: License :: OSI Approved :: Apache Software License
License-File: LICENSE
Requires-Dist: llm
Requires-Dist: httpx
Provides-Extra: test
Requires-Dist: pytest; extra == "test"
Requires-Dist: pytest-recording; extra == "test"
